{
        "intents": [
        {
                "tag": "greeting",
                "patterns": ["Hi", "Is anyone there?", "Hello", "Good day", "Whats up", "Hey"],
                "responses": ["Hello", "Hi", "Greetings", "Nice to meet you"],
                "context_set": ""
        },
        {
                "tag": "goodbye",
                "patterns": ["Cya", "See you later", "Goodbye", "I am Leaving", "Have a Good day", "Bye"],
                "responses": ["See you later", "Goodbye", "Bye", "Later!"],
                "context_set": ""
        },
        {
                "tag": "age",
                "patterns": ["How old", "What is your age", "How old are you", "Age?"],
                "responses": ["I was created in 2021"],
                "context_set": ""
        },
        {
                "tag": "name",
                "patterns": ["What is your name", "What should I call you", "Whats your name?", "Your name"],
                "responses": ["You can call me J.A.D.A.I", "Just call me J.A.D.A.I", "I'm J.A.D.A.I aka Just Another Discord Artificial Intelligence"],
                "context_set": ""
        },
        {
                "tag": "sad",
                "patterns": ["Sad", "Depressed", "Unhappy", "Angry", "Miserable"],
                "responses": ["Cheer up", "Hang in there", "Never give up", "You are great"],
                "context_set": ""
        },
        {
                "tag": "compliment",
                "patterns": ["Thanks", "Thank you", "Nice one", "Helped","Well said"],
                "responses": ["You're welcome", "No problem", "It's nothing", "I'm glad I could help"],
                "context_set": ""
        }
   ]
}